STT/__init__.py
RoSTT-0.1.dist-info/METADATA
RoSTT-0.1.dist-info/WHEEL
RoSTT-0.1.dist-info/top_level.txt
RoSTT-0.1.dist-info/RECORD
