Metadata-Version: 2.1
Name: RoSTT
Version: 0.1
Summary: this is a speech to text recognition package created by Rohan Bhosale
Author: Rohan Bhosale
